gemclus/__init__.py
gemclus/_base_gemini.py
gemclus/_constraints.py
gemclus/mlcl.py
gemclus/data/__init__.py
gemclus/data/synthetic_data.py
gemclus/gemini/__init__.py
gemclus/gemini/_base_loss.py
gemclus/gemini/_fdivergences.py
gemclus/gemini/_geomdistances.py
gemclus/gemini/_utils.py
gemclus/linear/__init__.py
gemclus/linear/_linear_geminis.py
gemclus/mlp/__init__.py
gemclus/mlp/_mlp_geminis.py
gemclus/nonparametric/__init__.py
gemclus/nonparametric/_categorical_models.py
gemclus/sparse/__init__.py
gemclus/sparse/_base_sparse.py
gemclus/sparse/_linear_sparse.py
gemclus/sparse/_mlp_sparse.py
gemclus/sparse/_prox_grad.py
gemclus/tests/__init__.py
gemclus/tests/test_data.py
gemclus/tests/test_default.py
gemclus/tests/test_mcml.py
gemclus/tests/test_objectives.py
gemclus/tests/test_path.py
gemclus/tests/test_trees.py
gemclus/tree/__init__.py
gemclus/tree/_utils.cp313-win_amd64.pyd
gemclus/tree/_utils.cpp
gemclus/tree/_utils.pyx
gemclus/tree/douglas.py
gemclus/tree/kauri.py
gemclus-1.1.1.dist-info/licenses/LICENSE
gemclus-1.1.1.dist-info/METADATA
gemclus-1.1.1.dist-info/WHEEL
gemclus-1.1.1.dist-info/top_level.txt
gemclus-1.1.1.dist-info/RECORD
