Metadata-Version: 2.4
Name: gemclus
Version: 1.1.1
Summary: A package for performing discriminative clustering with gemini-trained models
Author-email: Louis Ohl <louis.ohl@liu.se>
Maintainer-email: Louis Ohl <louis.ohl@liu.se>
License-Expression: GPL-3.0-or-later
Project-URL: Homepage, https://gemini-clustering.github.io/
Project-URL: Documentation, https://gemini-clustering.github.io/
Project-URL: Repository, https://github.com/gemini-clustering/GemClus
Project-URL: Changelog, https://gemini-clustering.github.io/history.html
Classifier: Intended Audience :: Science/Research
Classifier: Intended Audience :: Developers
Classifier: Intended Audience :: Education
Classifier: Programming Language :: Python
Classifier: Topic :: Utilities
Classifier: Topic :: Scientific/Engineering
Classifier: Topic :: Scientific/Engineering :: Artificial Intelligence
Classifier: Topic :: Scientific/Engineering :: Information Analysis
Classifier: Operating System :: Microsoft :: Windows
Classifier: Operating System :: POSIX
Classifier: Operating System :: Unix
Classifier: Operating System :: MacOS
Classifier: Programming Language :: Python :: 3.8
Classifier: Programming Language :: Python :: 3.9
Classifier: Programming Language :: Python :: 3.10
Classifier: Programming Language :: Python :: 3.11
Classifier: Programming Language :: Python :: 3.12
Requires-Python: >=3.8
License-File: LICENSE
Requires-Dist: numpy
Requires-Dist: scipy
Requires-Dist: scikit-learn
Requires-Dist: pot>=0.8.1
Provides-Extra: tests
Requires-Dist: pytest; extra == "tests"
Requires-Dist: pytest-cov; extra == "tests"
Provides-Extra: docs
Requires-Dist: sphinx; extra == "docs"
Requires-Dist: sphinx-gallery; extra == "docs"
Requires-Dist: sphinx_rtd_theme; extra == "docs"
Requires-Dist: numpydoc; extra == "docs"
Requires-Dist: matplotlib; extra == "docs"
Dynamic: license-file
